n_utils/__init__.py
n_utils/account_utils.py
n_utils/aws_infra_util.py
n_utils/az_util.py
n_utils/bw_util.py
n_utils/cf_bootstrap.py
n_utils/cf_deploy.py
n_utils/cli.py
n_utils/cloudfront_utils.py
n_utils/connect.py
n_utils/ecr_utils.py
n_utils/ecs_utils.py
n_utils/git_utils.py
n_utils/iam_utils.py
n_utils/log_events.py
n_utils/lp_util.py
n_utils/maven_utils.py
n_utils/mfa_utils.py
n_utils/nameless-dt-enable-profile.py
n_utils/nameless-dt-load-project-env.py
n_utils/ndt.py
n_utils/ndt_project.py
n_utils/profile_util.py
n_utils/project_util.py
n_utils/route53_util.py
n_utils/tf_utils.py
n_utils/utils.py
n_utils/writer.py
n_utils/yuuuu3332111i1l1i.py
n_utils/includes/apache_tools.sh
n_utils/includes/autocomplete-helpers.sh
n_utils/includes/aws_domainjoin.sh
n_utils/includes/aws_tools.sh
n_utils/includes/bake-docker.sh
n_utils/includes/bake-image.sh
n_utils/includes/bake-image.yml
n_utils/includes/bake-tags.yaml
n_utils/includes/bake-win-image.yml
n_utils/includes/cloud-init-firewall-cmd.te
n_utils/includes/cloud_init_footer.sh
n_utils/includes/cloud_init_functions.sh
n_utils/includes/common_tools.sh
n_utils/includes/deploy-azure.sh
n_utils/includes/deploy-cdk.sh
n_utils/includes/deploy-serverless.sh
n_utils/includes/deploy-stack.sh
n_utils/includes/deploy-terraform.sh
n_utils/includes/disk-by-drive-letter.ps1
n_utils/includes/ebs-functions.sh
n_utils/includes/fail2ban-rundir.te
n_utils/includes/fetch-secrets-lpass.sh
n_utils/includes/fetch-secrets-s3.sh
n_utils/includes/fetch-secrets-vault.sh
n_utils/includes/generate_jobs.groovy
n_utils/includes/get-docker.sh
n_utils/includes/hook.sh
n_utils/includes/install_tools.sh
n_utils/includes/jenkins_tools.sh
n_utils/includes/lastpass-login.sh
n_utils/includes/lastpass-logout.sh
n_utils/includes/letsencrypt.sh
n_utils/includes/manage-account.yaml
n_utils/includes/nexus_tools.sh
n_utils/includes/openvpn_tools.sh
n_utils/includes/prepare.ps1
n_utils/includes/prepare.sh
n_utils/includes/print-create-instructions.sh
nameless_deploy_tools-1.334.dist-info/licenses/LICENSE.txt
nameless_deploy_tools-1.334.dist-info/METADATA
nameless_deploy_tools-1.334.dist-info/WHEEL
nameless_deploy_tools-1.334.dist-info/entry_points.txt
nameless_deploy_tools-1.334.dist-info/top_level.txt
nameless_deploy_tools-1.334.dist-info/RECORD
