Metadata-Version: 2.4
Name: nameless-deploy-tools
Version: 1.334
Summary: Tools for deploying to AWS via CloudFormation and Serverless framework that support a pull request based workflow
Author-email: Pasi Niemi <pasi@nitor.com>
License: Apache-2.0
Project-URL: Homepage, https://github.com/NitorCreations/nameless-deploy-tools
Project-URL: Download, https://github.com/NitorCreations/nameless-deploy-tools/tarball/1.334
Classifier: Programming Language :: Python :: Implementation :: CPython
Requires-Python: >=3.9
License-File: LICENSE.txt
Requires-Dist: argcomplete
Requires-Dist: boto3
Requires-Dist: cloudformation-utils==0.0.2
Requires-Dist: configparser
Requires-Dist: ec2-utils>=0.39
Requires-Dist: ipaddr
Requires-Dist: jmespath
Requires-Dist: nitor-vault~=2.4
Requires-Dist: pyaml
Requires-Dist: pycryptodomex
Requires-Dist: Pygments
Requires-Dist: pyOpenSSL>=19.1.0
Requires-Dist: pyotp
Requires-Dist: pyqrcode
Requires-Dist: python-dateutil
Requires-Dist: PyYAML>=5.2
Requires-Dist: requests
Requires-Dist: scandir
Requires-Dist: termcolor
Requires-Dist: pypiwin32; platform_system == "Windows"
Requires-Dist: win-unicode-console; platform_system == "Windows"
Requires-Dist: wmi; platform_system == "Windows"
Provides-Extra: testing
Requires-Dist: coverage; extra == "testing"
Requires-Dist: mock; extra == "testing"
Requires-Dist: pytest-cov; extra == "testing"
Requires-Dist: pytest-mock; extra == "testing"
Requires-Dist: pytest; extra == "testing"
Provides-Extra: dev
Requires-Dist: pip-tools; extra == "dev"
Requires-Dist: ruff; extra == "dev"
Provides-Extra: build
Requires-Dist: build; extra == "build"
Requires-Dist: setuptools; extra == "build"
Requires-Dist: twine; extra == "build"
Requires-Dist: wheel; extra == "build"
Dynamic: license-file
